packtest/__init__.py
packtest/core.py
packtest551-0.1.9.dist-info/LICENSE
packtest551-0.1.9.dist-info/METADATA
packtest551-0.1.9.dist-info/WHEEL
packtest551-0.1.9.dist-info/top_level.txt
packtest551-0.1.9.dist-info/RECORD
