Metadata-Version: 2.1
Name: packtest551
Version: 0.1.9
Summary: asdfasdf
Author: asdf
License-File: LICENSE
Requires-Dist: numpy >=1.10
Requires-Dist: pandas
